termux_language_server/__init__.py
termux_language_server/__main__.py
termux_language_server/_metainfo.py
termux_language_server/_shtab.py
termux_language_server/_version.py
termux_language_server/finders.py
termux_language_server/py.typed
termux_language_server/schema.py
termux_language_server/server.py
termux_language_server/utils.py
termux_language_server/assets/jinja2/template.md.j2
termux_language_server/assets/json/PKGBUILD.json
termux_language_server/assets/json/build.sh.json
termux_language_server/assets/json/color.map.json
termux_language_server/assets/json/devscripts.conf.json
termux_language_server/assets/json/ebuild.json
termux_language_server/assets/json/install.json
termux_language_server/assets/json/make.conf.json
termux_language_server/assets/json/makepkg.conf.json
termux_language_server/assets/json/mdd.json
termux_language_server/assets/json/subpackage.sh.json
termux_language_server/assets/queries/mingw.scm
termux_language_server/assets/queries/package.scm
termux_language_server/misc/__init__.py
termux_language_server/misc/color_map.py
termux_language_server/misc/ebuild.py
termux_language_server/misc/licenses.py
termux_language_server/misc/make_conf.py
termux_language_server/misc/makepkg_conf.py
termux_language_server/misc/pkgbuild.py
termux_language_server/misc/termux.py
termux_language_server/packages/__init__.py
termux_language_server/packages/pkgbuild.py
termux_language_server/tools/namcap.py
termux_language_server-0.0.31.data/data/share/bash-completion/completions/pkgbuild-language-server
termux_language_server-0.0.31.data/data/share/bash-completion/completions/portage-language-server
termux_language_server-0.0.31.data/data/share/bash-completion/completions/termux-language-server
termux_language_server-0.0.31.data/data/share/man/man1/pkgbuild-language-server.1
termux_language_server-0.0.31.data/data/share/man/man1/portage-language-server.1
termux_language_server-0.0.31.data/data/share/man/man1/termux-language-server.1
termux_language_server-0.0.31.dist-info/licenses/LICENSE
termux_language_server-0.0.31.dist-info/METADATA
termux_language_server-0.0.31.dist-info/WHEEL
termux_language_server-0.0.31.dist-info/entry_points.txt
termux_language_server-0.0.31.dist-info/top_level.txt
termux_language_server-0.0.31.dist-info/RECORD
